style_bert_vits2/.editorconfig
style_bert_vits2/__init__.py
style_bert_vits2/constants.py
style_bert_vits2/logging.py
style_bert_vits2/tts_model.py
style_bert_vits2/voice.py
style_bert_vits2/models/__init__.py
style_bert_vits2/models/attentions.py
style_bert_vits2/models/commons.py
style_bert_vits2/models/hyper_parameters.py
style_bert_vits2/models/infer.py
style_bert_vits2/models/models.py
style_bert_vits2/models/models_jp_extra.py
style_bert_vits2/models/modules.py
style_bert_vits2/models/monotonic_alignment.py
style_bert_vits2/models/transforms.py
style_bert_vits2/models/utils/__init__.py
style_bert_vits2/models/utils/checkpoints.py
style_bert_vits2/models/utils/safetensors.py
style_bert_vits2/nlp/__init__.py
style_bert_vits2/nlp/bert_models.py
style_bert_vits2/nlp/symbols.py
style_bert_vits2/nlp/chinese/__init__.py
style_bert_vits2/nlp/chinese/bert_feature.py
style_bert_vits2/nlp/chinese/g2p.py
style_bert_vits2/nlp/chinese/normalizer.py
style_bert_vits2/nlp/chinese/opencpop-strict.txt
style_bert_vits2/nlp/chinese/tone_sandhi.py
style_bert_vits2/nlp/english/__init__.py
style_bert_vits2/nlp/english/bert_feature.py
style_bert_vits2/nlp/english/cmudict.py
style_bert_vits2/nlp/english/cmudict.rep
style_bert_vits2/nlp/english/cmudict_cache.pickle
style_bert_vits2/nlp/english/g2p.py
style_bert_vits2/nlp/english/normalizer.py
style_bert_vits2/nlp/japanese/__init__.py
style_bert_vits2/nlp/japanese/bert_feature.py
style_bert_vits2/nlp/japanese/g2p.py
style_bert_vits2/nlp/japanese/g2p_utils.py
style_bert_vits2/nlp/japanese/mora_list.py
style_bert_vits2/nlp/japanese/normalizer.py
style_bert_vits2/nlp/japanese/pyopenjtalk_worker/__init__.py
style_bert_vits2/nlp/japanese/pyopenjtalk_worker/__main__.py
style_bert_vits2/nlp/japanese/pyopenjtalk_worker/worker_client.py
style_bert_vits2/nlp/japanese/pyopenjtalk_worker/worker_common.py
style_bert_vits2/nlp/japanese/pyopenjtalk_worker/worker_server.py
style_bert_vits2/nlp/japanese/user_dict/README.md
style_bert_vits2-2.5.0.dist-info/METADATA
style_bert_vits2-2.5.0.dist-info/WHEEL
style_bert_vits2-2.5.0.dist-info/licenses/LICENSE
style_bert_vits2-2.5.0.dist-info/RECORD
