Metadata-Version: 2.3
Name: style-bert-vits2
Version: 2.5.0
Summary: Style-Bert-VITS2: Bert-VITS2 with more controllable voice styles.
Project-URL: Documentation, https://github.com/litagin02/Style-Bert-VITS2#readme
Project-URL: Issues, https://github.com/litagin02/Style-Bert-VITS2/issues
Project-URL: Source, https://github.com/litagin02/Style-Bert-VITS2
Author-email: litagin02 <139731664+litagin02@users.noreply.github.com>
License-Expression: AGPL-3.0
License-File: LICENSE
Classifier: Development Status :: 4 - Beta
Classifier: Programming Language :: Python
Classifier: Programming Language :: Python :: 3.9
Classifier: Programming Language :: Python :: 3.10
Classifier: Programming Language :: Python :: 3.11
Classifier: Programming Language :: Python :: Implementation :: CPython
Requires-Python: >=3.9
Requires-Dist: cmudict
Requires-Dist: cn2an
Requires-Dist: g2p-en
Requires-Dist: jieba
Requires-Dist: loguru
Requires-Dist: num2words
Requires-Dist: numba
Requires-Dist: numpy
Requires-Dist: pydantic>=2.0
Requires-Dist: pyopenjtalk-dict
Requires-Dist: pypinyin
Requires-Dist: pyworld-prebuilt
Requires-Dist: safetensors
Requires-Dist: torch>=2.1
Requires-Dist: transformers
